saviialib/__init__.py
saviialib/general_types/__init__.py
saviialib/general_types/api/__init__.py
saviialib/general_types/api/saviia_api_types.py
saviialib/general_types/api/saviia_backup_api_types.py
saviialib/general_types/api/saviia_netcamera_api_types.py
saviialib/general_types/api/saviia_shakes_api_types.py
saviialib/general_types/api/saviia_thies_api_types.py
saviialib/general_types/error_types/__init__.py
saviialib/general_types/error_types/api/__init__.py
saviialib/general_types/error_types/api/saviia_api_error_types.py
saviialib/general_types/error_types/api/saviia_netcamera_error_types.py
saviialib/general_types/error_types/common/__init__.py
saviialib/general_types/error_types/common/common_types.py
saviialib/libs/directory_client/__init__.py
saviialib/libs/directory_client/client/os_client.py
saviialib/libs/directory_client/directory_client.py
saviialib/libs/directory_client/directory_client_contract.py
saviialib/libs/directory_client/types/directory_client_types.py
saviialib/libs/files_client/__init__.py
saviialib/libs/files_client/clients/aiofiles_client.py
saviialib/libs/files_client/clients/csv_client.py
saviialib/libs/files_client/files_client.py
saviialib/libs/files_client/files_client_contract.py
saviialib/libs/files_client/types/files_client_types.py
saviialib/libs/ftp_client/__init__.py
saviialib/libs/ftp_client/clients/__init__.py
saviialib/libs/ftp_client/clients/aioftp_client.py
saviialib/libs/ftp_client/clients/ftplib_client.py
saviialib/libs/ftp_client/ftp_client.py
saviialib/libs/ftp_client/ftp_client_contract.py
saviialib/libs/ftp_client/types/__init__.py
saviialib/libs/ftp_client/types/ftp_client_types.py
saviialib/libs/log_client/__init__.py
saviialib/libs/log_client/log_client.py
saviialib/libs/log_client/log_client_contract.py
saviialib/libs/log_client/logging_client/logging_client.py
saviialib/libs/log_client/types/__init__.py
saviialib/libs/log_client/types/log_client_types.py
saviialib/libs/log_client/utils/log_client_utils.py
saviialib-1.10.0.dist-info/METADATA
saviialib-1.10.0.dist-info/WHEEL
saviialib-1.10.0.dist-info/licenses/LICENSE
saviialib-1.10.0.dist-info/RECORD
