Metadata-Version: 2.4
Name: saviialib
Version: 1.10.0
Summary: A client library for IoT projects in the RCER initiative
License: MIT
License-File: LICENSE
Author: pedropablozavalat
Requires-Python: >=3.11,<4.0
Classifier: License :: OSI Approved :: MIT License
Classifier: Programming Language :: Python :: 3
Classifier: Programming Language :: Python :: 3.11
Classifier: Programming Language :: Python :: 3.12
Classifier: Programming Language :: Python :: 3.13
Classifier: Programming Language :: Python :: 3.14
Requires-Dist: aiofiles
Requires-Dist: aioftp
Requires-Dist: aiohttp
Requires-Dist: asyncssh (==2.21.1)
Requires-Dist: bitarray
Requires-Dist: build
Requires-Dist: certifi
Requires-Dist: dotenv (>=0.9.9,<0.10.0)
Requires-Dist: ffmpeg-asyncio (==0.1.3)
Requires-Dist: jsonschema (==4.25.1)
Requires-Dist: numpy (>=2.2.0,<2.4.0)
Requires-Dist: pandas (>=2.2.3)
